spotlight_in_windows_seige/__init__.py
spotlight_in_windows_seige/main.py
spotlight_in_windows_seige-0.1.4.dist-info/entry_points.txt
spotlight_in_windows_seige-0.1.4.dist-info/METADATA
spotlight_in_windows_seige-0.1.4.dist-info/WHEEL
spotlight_in_windows_seige-0.1.4.dist-info/RECORD
