Metadata-Version: 2.4
Name: spotlight-in-windows-seige
Version: 0.1.4
Summary: A Windows search utility inspired by Spotlight, with a fluent design and hot-corner activation.
License: MIT
Author: William Gu
Author-email: williamnumismatics@gmail.com
Requires-Python: >=3.9,<4.0
Classifier: License :: OSI Approved :: MIT License
Classifier: Programming Language :: Python :: 3
Classifier: Programming Language :: Python :: 3.9
Classifier: Programming Language :: Python :: 3.10
Classifier: Programming Language :: Python :: 3.11
Classifier: Programming Language :: Python :: 3.12
Classifier: Programming Language :: Python :: 3.13
Classifier: Programming Language :: Python :: 3.14
Requires-Dist: fuzzywuzzy
Requires-Dist: psutil
Requires-Dist: pynput
Requires-Dist: pyperclip
Requires-Dist: python-Levenshtein
Requires-Dist: pywin32
Requires-Dist: watchdog
